setup.py
PenguinMol3D/LICENSE.txt
PenguinMol3D/README.md
PenguinMol3D/__init__.py
PenguinMol3D/display_molecule.py
PenguinMol3D/glfw_bpr_example.py
PenguinMol3D/glfw_custom_material_example.py
PenguinMol3D/glfw_pbr_example.py
PenguinMol3D/glfw_surface_example.py
PenguinMol3D/penguinone.sdf
PenguinMol3D.egg-info/PKG-INFO
PenguinMol3D.egg-info/SOURCES.txt
PenguinMol3D.egg-info/dependency_links.txt
PenguinMol3D.egg-info/requires.txt
PenguinMol3D.egg-info/top_level.txt
PenguinMol3D/factories/__init__.py
PenguinMol3D/factories/atoms_factory.py
PenguinMol3D/factories/base_factory.py
PenguinMol3D/factories/bonds_factory.py
PenguinMol3D/general/__init__.py
PenguinMol3D/general/attribute.py
PenguinMol3D/general/bounding_box.py
PenguinMol3D/general/globals.py
PenguinMol3D/general/opengl_utils.py
PenguinMol3D/general/renderer.py
PenguinMol3D/general/uniform.py
PenguinMol3D/geometries/__init__.py
PenguinMol3D/geometries/base_continuous_geometry.py
PenguinMol3D/geometries/base_geometry_group.py
PenguinMol3D/geometries/base_parametric_geometry.py
PenguinMol3D/geometries/base_singular_geometry.py
PenguinMol3D/geometries/atoms/__init__.py
PenguinMol3D/geometries/atoms/atoms_geometry.py
PenguinMol3D/geometries/atoms/base_atom_geometry.py
PenguinMol3D/geometries/bonds/__init__.py
PenguinMol3D/geometries/bonds/base_bond_geometry.py
PenguinMol3D/geometries/bonds/bonds_geometry.py
PenguinMol3D/geometries/shapes/__init__.py
PenguinMol3D/geometries/shapes/ellipsoid.py
PenguinMol3D/geometries/shapes/sphere.py
PenguinMol3D/materials/__init__.py
PenguinMol3D/materials/base_material.py
PenguinMol3D/materials/pbr_material.py
PenguinMol3D/materials/phong_material.py
PenguinMol3D/materials/phong_materials.py
PenguinMol3D/materials/shaders/__init__.py
PenguinMol3D/materials/shaders/base.vert
PenguinMol3D/materials/shaders/blinn_phong_material.frag
PenguinMol3D/materials/shaders/instanced.vert
PenguinMol3D/materials/shaders/pbr_material.frag
PenguinMol3D/materials/shaders/phong_material.frag
PenguinMol3D/objects/__init__.py
PenguinMol3D/objects/base_object_3d.py
PenguinMol3D/objects/camera.py
PenguinMol3D/objects/group.py
PenguinMol3D/objects/mesh.py
