Metadata-Version: 2.1
Name: PenguinMol3D
Version: 0.1.3
Summary: 3D visualization of small compounds
Author: Yevhen Kustovskiy
Author-email: ykustovskiy@gmail.com
Project-URL: Homepage, https://github.com/YevhenKustovskiy/penguinemol3d
Classifier: Programming Language :: Python :: 3
Classifier: License :: OSI Approved :: GNU General Public License v2 (GPLv2)
Classifier: Operating System :: OS Independent
Requires-Python: >=3.10
Requires-Dist: numpy
Requires-Dist: rdkit
Requires-Dist: PyOpenGL
Requires-Dist: PyOpenGL_accelerate
Requires-Dist: glfw
Requires-Dist: Pillow
